COPYRIGHT.txt
LICENSE.txt
bootstrap.py
buildout.cfg
setup.py
versions.cfg
docs/HISTORY.txt
src/megrok/__init__.py
src/megrok.z3ctable.egg-info/PKG-INFO
src/megrok.z3ctable.egg-info/SOURCES.txt
src/megrok.z3ctable.egg-info/dependency_links.txt
src/megrok.z3ctable.egg-info/entry_points.txt
src/megrok.z3ctable.egg-info/namespace_packages.txt
src/megrok.z3ctable.egg-info/not-zip-safe
src/megrok.z3ctable.egg-info/requires.txt
src/megrok.z3ctable.egg-info/top_level.txt
src/megrok/z3ctable/CREDITS.txt
src/megrok/z3ctable/README.txt
src/megrok/z3ctable/__init__.py
src/megrok/z3ctable/components.py
src/megrok/z3ctable/configure.zcml
src/megrok/z3ctable/directive.py
src/megrok/z3ctable/meta.py
src/megrok/z3ctable/meta.zcml
src/megrok/z3ctable/tests/__init__.py
src/megrok/z3ctable/tests/adapters.py
src/megrok/z3ctable/tests/ftesting.zcml
src/megrok/z3ctable/tests/implicit.py
src/megrok/z3ctable/tests/test_general.py
src/megrok/z3ctable/tests/views.py
src/megrok/z3ctable/tests/views_templates/tablelayout.pt
src/megrok/z3ctable/tests/views_templates/tablepageinlayout.pt
src/megrok/z3ctable/tests/views_templates/tableview.pt
src/megrok/z3ctable/tests/views_templates/tw.pt