Metadata-Version: 1.1
Name: megrok.z3ctable
Version: 1.6.0
Summary: A table component package for Grok based on z3c.table.
Home-page: http://pypi.python.org/pypi/megrok.z3ctable
Author: Souheil Chelfouh
Author-email: trollfot@gmail.com
License: ZPL
Keywords: grok table zope3
Platform: UNKNOWN
Classifier: Framework :: Zope3
Classifier: Programming Language :: Python
Classifier: Programming Language :: Zope
Classifier: Intended Audience :: Developers
Classifier: Development Status :: 4 - Beta
Classifier: Topic :: Software Development :: Libraries :: Python Modules
